fair_numbers/__init__.py
fair_numbers/fair_numbers.py
fair_numbers-1.1.dist-info/LICENSE
fair_numbers-1.1.dist-info/METADATA
fair_numbers-1.1.dist-info/WHEEL
fair_numbers-1.1.dist-info/top_level.txt
fair_numbers-1.1.dist-info/RECORD
