Metadata-Version: 2.1
Name: fair-numbers
Version: 1.1
Summary: Formating long numbers
Home-page: https://gitlab.com/xalion/pretty-numbers
Author: Xalion
Author-email: xalion67@gmail.com
License: UNKNOWN
Platform: UNKNOWN
Classifier: Programming Language :: Python :: 3
Classifier: License :: OSI Approved :: MIT License
Classifier: Operating System :: OS Independent
